pymakefile/__init__.py
pymakefile/pymakefile.py
pymakefile-0.1.2.dist-info/entry_points.txt
pymakefile-0.1.2.dist-info/LICENSE
pymakefile-0.1.2.dist-info/WHEEL
pymakefile-0.1.2.dist-info/METADATA
pymakefile-0.1.2.dist-info/RECORD
