Metadata-Version: 2.1
Name: pymakefile
Version: 0.1.2
Summary: Manage your Makefiles from python
Home-page: https://github.com/willbackslash/pymakefile
License: MIT
Author: William
Author-email: macwilliamdlc@gmail.com
Requires-Python: >=3.8,<4.0
Classifier: License :: OSI Approved :: MIT License
Classifier: Programming Language :: Python :: 3
Classifier: Programming Language :: Python :: 3.8
Classifier: Programming Language :: Python :: 3.9
Requires-Dist: click (>=8.0.1,<9.0.0)
Project-URL: Repository, https://github.com/willbackslash/pymakefile
